LICENSE
MANIFEST.in
README.rst
requirements.txt
setup.py
alexandra/__init__.py
alexandra/app.py
alexandra/session.py
alexandra/util.py
alexandra/wsgi.py
alexandra.egg-info/PKG-INFO
alexandra.egg-info/SOURCES.txt
alexandra.egg-info/dependency_links.txt
alexandra.egg-info/requires.txt
alexandra.egg-info/top_level.txt