Metadata-Version: 1.1
Name: alexandra
Version: 0.4.0
Summary: Toolkit for writing Amazon Alexa skills as web services
Home-page: https://github.com/erik/alexandra
Author: Erik Price
Author-email: UNKNOWN
License: ISC
Platform: UNKNOWN
Classifier: Development Status :: 5 - Production/Stable
Classifier: Intended Audience :: Developers
Classifier: License :: OSI Approved :: ISC License (ISCL)
Classifier: Programming Language :: Python :: 2.7
Classifier: Programming Language :: Python :: 3.6
Classifier: Topic :: Home Automation
Classifier: Topic :: Internet :: WWW/HTTP :: WSGI :: Application
Classifier: Topic :: Software Development :: Libraries :: Application Frameworks
